<?xml version="1.0" encoding="utf-8"?><DEFECTS><DEFECT>
    <SFA>
      <FILEPATH>c:\md\md3.0\md3.0\</FILEPATH>
      <FILENAME>md3.0.cpp</FILENAME>
      <LINE>1014</LINE>
      <COLUMN>7</COLUMN>
    </SFA>
    <DEFECTCODE>6031</DEFECTCODE>
    <DESCRIPTION>Возвращаемое значение пропущено: "fscanf".</DESCRIPTION>
    <FUNCTION>load_information_about_one_particle</FUNCTION>
    <DECORATED>?load_information_about_one_particle@@YAXPEAU_iobuf@@@Z</DECORATED>
    <FUNCLINE>1009</FUNCLINE>
    <PATH></PATH>
  </DEFECT><DEFECT>
    <SFA>
      <FILEPATH>c:\md\md3.0\md3.0\</FILEPATH>
      <FILENAME>md3.0.cpp</FILENAME>
      <LINE>1017</LINE>
      <COLUMN>7</COLUMN>
    </SFA>
    <DEFECTCODE>6031</DEFECTCODE>
    <DESCRIPTION>Возвращаемое значение пропущено: "fscanf".</DESCRIPTION>
    <FUNCTION>load_information_about_one_particle</FUNCTION>
    <DECORATED>?load_information_about_one_particle@@YAXPEAU_iobuf@@@Z</DECORATED>
    <FUNCLINE>1009</FUNCLINE>
    <PATH></PATH>
  </DEFECT><DEFECT>
    <SFA>
      <FILEPATH>c:\md\md3.0\md3.0\</FILEPATH>
      <FILENAME>md3.0.cpp</FILENAME>
      <LINE>1023</LINE>
      <COLUMN>7</COLUMN>
    </SFA>
    <DEFECTCODE>6031</DEFECTCODE>
    <DESCRIPTION>Возвращаемое значение пропущено: "fscanf".</DESCRIPTION>
    <FUNCTION>load_information_about_one_particle</FUNCTION>
    <DECORATED>?load_information_about_one_particle@@YAXPEAU_iobuf@@@Z</DECORATED>
    <FUNCLINE>1009</FUNCLINE>
    <PATH></PATH>
  </DEFECT><DEFECT>
    <SFA>
      <FILEPATH>c:\md\md3.0\md3.0\</FILEPATH>
      <FILENAME>md3.0.cpp</FILENAME>
      <LINE>1083</LINE>
      <COLUMN>7</COLUMN>
    </SFA>
    <DEFECTCODE>6385</DEFECTCODE>
    <DESCRIPTION>Чтение недопустимых данных из "boxes_yz":  доступный для чтения объем равен "1840000000" байт, однако считать можно только "y_box" байт.</DESCRIPTION>
    <FUNCTION>load_information_about_one_particle</FUNCTION>
    <DECORATED>?load_information_about_one_particle@@YAXPEAU_iobuf@@@Z</DECORATED>
    <FUNCLINE>1009</FUNCLINE>
    <PROBABILITY>1</PROBABILITY>
    <RANK>4</RANK>
    <CATEGORY>
      <RULECATEGORY>mspft</RULECATEGORY>
    </CATEGORY>
    <PATH>
      <SFA>
        <FILEPATH>c:\md\md3.0\md3.0\</FILEPATH>
        <FILENAME>md3.0.cpp</FILENAME>
        <LINE>1010</LINE>
        <COLUMN>8</COLUMN>
      </SFA>
      <SFA>
        <FILEPATH>c:\md\md3.0\md3.0\</FILEPATH>
        <FILENAME>md3.0.cpp</FILENAME>
        <LINE>1010</LINE>
        <COLUMN>12</COLUMN>
      </SFA>
      <SFA>
        <FILEPATH>c:\md\md3.0\md3.0\</FILEPATH>
        <FILENAME>md3.0.cpp</FILENAME>
        <LINE>1010</LINE>
        <COLUMN>16</COLUMN>
      </SFA>
      <SFA>
        <FILEPATH>c:\md\md3.0\md3.0\</FILEPATH>
        <FILENAME>md3.0.cpp</FILENAME>
        <LINE>1011</LINE>
        <COLUMN>6</COLUMN>
      </SFA>
      <SFA>
        <FILEPATH>c:\md\md3.0\md3.0\</FILEPATH>
        <FILENAME>md3.0.cpp</FILENAME>
        <LINE>1011</LINE>
        <COLUMN>9</COLUMN>
      </SFA>
      <SFA>
        <FILEPATH>c:\md\md3.0\md3.0\</FILEPATH>
        <FILENAME>md3.0.cpp</FILENAME>
        <LINE>1011</LINE>
        <COLUMN>16</COLUMN>
      </SFA>
      <SFA>
        <FILEPATH>c:\md\md3.0\md3.0\</FILEPATH>
        <FILENAME>md3.0.cpp</FILENAME>
        <LINE>1011</LINE>
        <COLUMN>23</COLUMN>
      </SFA>
      <SFA>
        <FILEPATH>c:\md\md3.0\md3.0\</FILEPATH>
        <FILENAME>md3.0.cpp</FILENAME>
        <LINE>1011</LINE>
        <COLUMN>30</COLUMN>
      </SFA>
      <SFA>
        <FILEPATH>c:\md\md3.0\md3.0\</FILEPATH>
        <FILENAME>md3.0.cpp</FILENAME>
        <LINE>1014</LINE>
        <COLUMN>7</COLUMN>
      </SFA>
      <SFA>
        <FILEPATH>c:\md\md3.0\md3.0\</FILEPATH>
        <FILENAME>md3.0.cpp</FILENAME>
        <LINE>1017</LINE>
        <COLUMN>7</COLUMN>
      </SFA>
      <SFA>
        <FILEPATH>c:\md\md3.0\md3.0\</FILEPATH>
        <FILENAME>md3.0.cpp</FILENAME>
        <LINE>1018</LINE>
        <COLUMN>19</COLUMN>
      </SFA>
      <SFA>
        <FILEPATH>c:\md\md3.0\md3.0\</FILEPATH>
        <FILENAME>md3.0.cpp</FILENAME>
        <LINE>1019</LINE>
        <COLUMN>19</COLUMN>
      </SFA>
      <SFA>
        <FILEPATH>c:\md\md3.0\md3.0\</FILEPATH>
        <FILENAME>md3.0.cpp</FILENAME>
        <LINE>1020</LINE>
        <COLUMN>19</COLUMN>
      </SFA>
      <SFA>
        <FILEPATH>c:\md\md3.0\md3.0\</FILEPATH>
        <FILENAME>md3.0.cpp</FILENAME>
        <LINE>1023</LINE>
        <COLUMN>7</COLUMN>
      </SFA>
      <SFA>
        <FILEPATH>c:\md\md3.0\md3.0\</FILEPATH>
        <FILENAME>md3.0.cpp</FILENAME>
        <LINE>1024</LINE>
        <COLUMN>17</COLUMN>
      </SFA>
      <SFA>
        <FILEPATH>c:\md\md3.0\md3.0\</FILEPATH>
        <FILENAME>md3.0.cpp</FILENAME>
        <LINE>1025</LINE>
        <COLUMN>17</COLUMN>
      </SFA>
      <SFA>
        <FILEPATH>c:\md\md3.0\md3.0\</FILEPATH>
        <FILENAME>md3.0.cpp</FILENAME>
        <LINE>1026</LINE>
        <COLUMN>17</COLUMN>
      </SFA>
      <SFA>
        <FILEPATH>c:\md\md3.0\md3.0\</FILEPATH>
        <FILENAME>md3.0.cpp</FILENAME>
        <LINE>1028</LINE>
        <COLUMN>16</COLUMN>
      </SFA>
      <SFA>
        <FILEPATH>c:\md\md3.0\md3.0\</FILEPATH>
        <FILENAME>md3.0.cpp</FILENAME>
        <LINE>1029</LINE>
        <COLUMN>17</COLUMN>
      </SFA>
      <SFA>
        <FILEPATH>c:\md\md3.0\md3.0\</FILEPATH>
        <FILENAME>md3.0.cpp</FILENAME>
        <LINE>1030</LINE>
        <COLUMN>17</COLUMN>
      </SFA>
      <SFA>
        <FILEPATH>c:\md\md3.0\md3.0\</FILEPATH>
        <FILENAME>md3.0.cpp</FILENAME>
        <LINE>1032</LINE>
        <COLUMN>23</COLUMN>
        <KEYEVENT>
          <ID>1</ID>
          <KIND>ветвь</KIND>
          <IMPORTANCE>Full</IMPORTANCE>
          <MESSAGE>Пропустить эту ветвь (предполагается, что "particles[i].y[0]&lt;particle_Rx2" равно false)</MESSAGE>
        </KEYEVENT>
      </SFA>
      <SFA>
        <FILEPATH>c:\md\md3.0\md3.0\</FILEPATH>
        <FILENAME>md3.0.cpp</FILENAME>
        <LINE>1037</LINE>
        <COLUMN>23</COLUMN>
        <KEYEVENT>
          <ID>2</ID>
          <KIND>ветвь</KIND>
          <IMPORTANCE>Full</IMPORTANCE>
          <MESSAGE>Пропустить эту ветвь (предполагается, что "&lt;условие ветви&gt;" равно false)</MESSAGE>
        </KEYEVENT>
      </SFA>
      <SFA>
        <FILEPATH>c:\md\md3.0\md3.0\</FILEPATH>
        <FILENAME>md3.0.cpp</FILENAME>
        <LINE>1042</LINE>
        <COLUMN>23</COLUMN>
        <KEYEVENT>
          <ID>3</ID>
          <KIND>ветвь</KIND>
          <IMPORTANCE>Full</IMPORTANCE>
          <MESSAGE>Пропустить эту ветвь (предполагается, что "particles[i].z[0]&lt;particle_Rx2" равно false)</MESSAGE>
        </KEYEVENT>
      </SFA>
      <SFA>
        <FILEPATH>c:\md\md3.0\md3.0\</FILEPATH>
        <FILENAME>md3.0.cpp</FILENAME>
        <LINE>1047</LINE>
        <COLUMN>23</COLUMN>
        <KEYEVENT>
          <ID>4</ID>
          <KIND>ветвь</KIND>
          <IMPORTANCE>Full</IMPORTANCE>
          <MESSAGE>Пропустить эту ветвь (предполагается, что "&lt;условие ветви&gt;" равно false)</MESSAGE>
        </KEYEVENT>
      </SFA>
      <SFA>
        <FILEPATH>c:\md\md3.0\md3.0\</FILEPATH>
        <FILENAME>md3.0.cpp</FILENAME>
        <LINE>1052</LINE>
        <COLUMN>29</COLUMN>
        <KEYEVENT>
          <ID>5</ID>
          <KIND>ветвь</KIND>
          <IMPORTANCE>Full</IMPORTANCE>
          <MESSAGE>Пропустить эту ветвь (предполагается, что "&lt;условие ветви&gt;" равно false)</MESSAGE>
        </KEYEVENT>
      </SFA>
      <SFA>
        <FILEPATH>c:\md\md3.0\md3.0\</FILEPATH>
        <FILENAME>md3.0.cpp</FILENAME>
        <LINE>1058</LINE>
        <COLUMN>15</COLUMN>
      </SFA>
      <SFA>
        <FILEPATH>c:\md\md3.0\md3.0\</FILEPATH>
        <FILENAME>md3.0.cpp</FILENAME>
        <LINE>1058</LINE>
        <COLUMN>24</COLUMN>
        <KEYEVENT>
          <ID>6</ID>
          <KIND>ветвь</KIND>
          <IMPORTANCE>Full</IMPORTANCE>
          <MESSAGE>Войти в этот цикл (предполагается "j&lt;4")</MESSAGE>
        </KEYEVENT>
      </SFA>
      <SFA>
        <FILEPATH>c:\md\md3.0\md3.0\</FILEPATH>
        <FILENAME>md3.0.cpp</FILENAME>
        <LINE>1059</LINE>
        <COLUMN>24</COLUMN>
        <KEYEVENT>
          <ID>7</ID>
          <KIND>ветвь</KIND>
          <IMPORTANCE>Full</IMPORTANCE>
          <MESSAGE>Войти в эту ветвь (предполагается "particles[i].x[j]&gt;0.000000")</MESSAGE>
        </KEYEVENT>
      </SFA>
      <SFA>
        <FILEPATH>c:\md\md3.0\md3.0\</FILEPATH>
        <FILENAME>md3.0.cpp</FILENAME>
        <LINE>1061</LINE>
        <COLUMN>9</COLUMN>
      </SFA>
      <SFA>
        <FILEPATH>c:\md\md3.0\md3.0\</FILEPATH>
        <FILENAME>md3.0.cpp</FILENAME>
        <LINE>1062</LINE>
        <COLUMN>9</COLUMN>
      </SFA>
      <SFA>
        <FILEPATH>c:\md\md3.0\md3.0\</FILEPATH>
        <FILENAME>md3.0.cpp</FILENAME>
        <LINE>1063</LINE>
        <COLUMN>9</COLUMN>
      </SFA>
      <SFA>
        <FILEPATH>c:\md\md3.0\md3.0\</FILEPATH>
        <FILENAME>md3.0.cpp</FILENAME>
        <LINE>1065</LINE>
        <COLUMN>60</COLUMN>
        <KEYEVENT>
          <ID>8</ID>
          <KIND>ветвь</KIND>
          <IMPORTANCE>Full</IMPORTANCE>
          <MESSAGE>Пропустить эту ветвь (предполагается, что "&lt;условие ветви&gt;" равно false)</MESSAGE>
        </KEYEVENT>
      </SFA>
      <SFA>
        <FILEPATH>c:\md\md3.0\md3.0\</FILEPATH>
        <FILENAME>md3.0.cpp</FILENAME>
        <LINE>1073</LINE>
        <COLUMN>13</COLUMN>
      </SFA>
      <SFA>
        <FILEPATH>c:\md\md3.0\md3.0\</FILEPATH>
        <FILENAME>md3.0.cpp</FILENAME>
        <LINE>1074</LINE>
        <COLUMN>13</COLUMN>
      </SFA>
      <SFA>
        <FILEPATH>c:\md\md3.0\md3.0\</FILEPATH>
        <FILENAME>md3.0.cpp</FILENAME>
        <LINE>1074</LINE>
        <COLUMN>24</COLUMN>
      </SFA>
      <SFA>
        <FILEPATH>c:\md\md3.0\md3.0\</FILEPATH>
        <FILENAME>md3.0.cpp</FILENAME>
        <LINE>1075</LINE>
        <COLUMN>13</COLUMN>
        <KEYEVENT>
          <ID>9</ID>
          <KIND>ветвь</KIND>
          <IMPORTANCE>Full</IMPORTANCE>
          <MESSAGE>Войти в эту ветвь (предполагается "y_box&gt;K")</MESSAGE>
        </KEYEVENT>
      </SFA>
      <SFA>
        <FILEPATH>c:\md\md3.0\md3.0\</FILEPATH>
        <FILENAME>md3.0.cpp</FILENAME>
        <LINE>1075</LINE>
        <COLUMN>24</COLUMN>
        <KEYEVENT>
          <ID>10</ID>
          <KIND>псевдоним</KIND>
          <IMPORTANCE>Essential</IMPORTANCE>
          <MESSAGE>(псевдоним) "y_box" получает значение "K"</MESSAGE>
        </KEYEVENT>
      </SFA>
      <SFA>
        <FILEPATH>c:\md\md3.0\md3.0\</FILEPATH>
        <FILENAME>md3.0.cpp</FILENAME>
        <LINE>1076</LINE>
        <COLUMN>13</COLUMN>
        <KEYEVENT>
          <ID>11</ID>
          <KIND>ветвь</KIND>
          <IMPORTANCE>Full</IMPORTANCE>
          <MESSAGE>Войти в эту ветвь (предполагается "z_box&gt;K")</MESSAGE>
        </KEYEVENT>
      </SFA>
      <SFA>
        <FILEPATH>c:\md\md3.0\md3.0\</FILEPATH>
        <FILENAME>md3.0.cpp</FILENAME>
        <LINE>1076</LINE>
        <COLUMN>24</COLUMN>
      </SFA>
      <SFA>
        <FILEPATH>c:\md\md3.0\md3.0\</FILEPATH>
        <FILENAME>md3.0.cpp</FILENAME>
        <LINE>1078</LINE>
        <COLUMN>25</COLUMN>
      </SFA>
      <SFA>
        <FILEPATH>c:\md\md3.0\md3.0\</FILEPATH>
        <FILENAME>md3.0.cpp</FILENAME>
        <LINE>1079</LINE>
        <COLUMN>25</COLUMN>
      </SFA>
      <SFA>
        <FILEPATH>c:\md\md3.0\md3.0\</FILEPATH>
        <FILENAME>md3.0.cpp</FILENAME>
        <LINE>1080</LINE>
        <COLUMN>25</COLUMN>
      </SFA>
      <SFA>
        <FILEPATH>c:\md\md3.0\md3.0\</FILEPATH>
        <FILENAME>md3.0.cpp</FILENAME>
        <LINE>1083</LINE>
        <COLUMN>7</COLUMN>
        <KEYEVENT>
          <ID>12</ID>
          <KIND>использование</KIND>
          <IMPORTANCE>Essential</IMPORTANCE>
          <MESSAGE>Недопустимая операция чтения из "boxes_yz[-1]" (доступный для чтения диапазон: от 0 до 99)</MESSAGE>
        </KEYEVENT>
      </SFA>
    </PATH>
  </DEFECT><DEFECT>
    <SFA>
      <FILEPATH>c:\md\md3.0\md3.0\</FILEPATH>
      <FILENAME>md3.0.cpp</FILENAME>
      <LINE>1084</LINE>
      <COLUMN>48</COLUMN>
    </SFA>
    <DEFECTCODE>6386</DEFECTCODE>
    <DESCRIPTION>Переполнение буфера при записи в "boxes_yz":  доступный для записи объем равен "1840000000" байт, однако записать можно только "y_box" байт.</DESCRIPTION>
    <FUNCTION>load_information_about_one_particle</FUNCTION>
    <DECORATED>?load_information_about_one_particle@@YAXPEAU_iobuf@@@Z</DECORATED>
    <FUNCLINE>1009</FUNCLINE>
    <PROBABILITY>1</PROBABILITY>
    <RANK>4</RANK>
    <CATEGORY>
      <RULECATEGORY>mspft</RULECATEGORY>
    </CATEGORY>
    <PATH>
      <SFA>
        <FILEPATH>c:\md\md3.0\md3.0\</FILEPATH>
        <FILENAME>md3.0.cpp</FILENAME>
        <LINE>1010</LINE>
        <COLUMN>8</COLUMN>
      </SFA>
      <SFA>
        <FILEPATH>c:\md\md3.0\md3.0\</FILEPATH>
        <FILENAME>md3.0.cpp</FILENAME>
        <LINE>1010</LINE>
        <COLUMN>12</COLUMN>
      </SFA>
      <SFA>
        <FILEPATH>c:\md\md3.0\md3.0\</FILEPATH>
        <FILENAME>md3.0.cpp</FILENAME>
        <LINE>1010</LINE>
        <COLUMN>16</COLUMN>
      </SFA>
      <SFA>
        <FILEPATH>c:\md\md3.0\md3.0\</FILEPATH>
        <FILENAME>md3.0.cpp</FILENAME>
        <LINE>1011</LINE>
        <COLUMN>6</COLUMN>
      </SFA>
      <SFA>
        <FILEPATH>c:\md\md3.0\md3.0\</FILEPATH>
        <FILENAME>md3.0.cpp</FILENAME>
        <LINE>1011</LINE>
        <COLUMN>9</COLUMN>
      </SFA>
      <SFA>
        <FILEPATH>c:\md\md3.0\md3.0\</FILEPATH>
        <FILENAME>md3.0.cpp</FILENAME>
        <LINE>1011</LINE>
        <COLUMN>16</COLUMN>
      </SFA>
      <SFA>
        <FILEPATH>c:\md\md3.0\md3.0\</FILEPATH>
        <FILENAME>md3.0.cpp</FILENAME>
        <LINE>1011</LINE>
        <COLUMN>23</COLUMN>
      </SFA>
      <SFA>
        <FILEPATH>c:\md\md3.0\md3.0\</FILEPATH>
        <FILENAME>md3.0.cpp</FILENAME>
        <LINE>1011</LINE>
        <COLUMN>30</COLUMN>
      </SFA>
      <SFA>
        <FILEPATH>c:\md\md3.0\md3.0\</FILEPATH>
        <FILENAME>md3.0.cpp</FILENAME>
        <LINE>1014</LINE>
        <COLUMN>7</COLUMN>
      </SFA>
      <SFA>
        <FILEPATH>c:\md\md3.0\md3.0\</FILEPATH>
        <FILENAME>md3.0.cpp</FILENAME>
        <LINE>1017</LINE>
        <COLUMN>7</COLUMN>
      </SFA>
      <SFA>
        <FILEPATH>c:\md\md3.0\md3.0\</FILEPATH>
        <FILENAME>md3.0.cpp</FILENAME>
        <LINE>1018</LINE>
        <COLUMN>19</COLUMN>
      </SFA>
      <SFA>
        <FILEPATH>c:\md\md3.0\md3.0\</FILEPATH>
        <FILENAME>md3.0.cpp</FILENAME>
        <LINE>1019</LINE>
        <COLUMN>19</COLUMN>
      </SFA>
      <SFA>
        <FILEPATH>c:\md\md3.0\md3.0\</FILEPATH>
        <FILENAME>md3.0.cpp</FILENAME>
        <LINE>1020</LINE>
        <COLUMN>19</COLUMN>
      </SFA>
      <SFA>
        <FILEPATH>c:\md\md3.0\md3.0\</FILEPATH>
        <FILENAME>md3.0.cpp</FILENAME>
        <LINE>1023</LINE>
        <COLUMN>7</COLUMN>
      </SFA>
      <SFA>
        <FILEPATH>c:\md\md3.0\md3.0\</FILEPATH>
        <FILENAME>md3.0.cpp</FILENAME>
        <LINE>1024</LINE>
        <COLUMN>17</COLUMN>
      </SFA>
      <SFA>
        <FILEPATH>c:\md\md3.0\md3.0\</FILEPATH>
        <FILENAME>md3.0.cpp</FILENAME>
        <LINE>1025</LINE>
        <COLUMN>17</COLUMN>
      </SFA>
      <SFA>
        <FILEPATH>c:\md\md3.0\md3.0\</FILEPATH>
        <FILENAME>md3.0.cpp</FILENAME>
        <LINE>1026</LINE>
        <COLUMN>17</COLUMN>
      </SFA>
      <SFA>
        <FILEPATH>c:\md\md3.0\md3.0\</FILEPATH>
        <FILENAME>md3.0.cpp</FILENAME>
        <LINE>1028</LINE>
        <COLUMN>16</COLUMN>
      </SFA>
      <SFA>
        <FILEPATH>c:\md\md3.0\md3.0\</FILEPATH>
        <FILENAME>md3.0.cpp</FILENAME>
        <LINE>1029</LINE>
        <COLUMN>17</COLUMN>
      </SFA>
      <SFA>
        <FILEPATH>c:\md\md3.0\md3.0\</FILEPATH>
        <FILENAME>md3.0.cpp</FILENAME>
        <LINE>1030</LINE>
        <COLUMN>17</COLUMN>
      </SFA>
      <SFA>
        <FILEPATH>c:\md\md3.0\md3.0\</FILEPATH>
        <FILENAME>md3.0.cpp</FILENAME>
        <LINE>1032</LINE>
        <COLUMN>23</COLUMN>
        <KEYEVENT>
          <ID>1</ID>
          <KIND>ветвь</KIND>
          <IMPORTANCE>Full</IMPORTANCE>
          <MESSAGE>Пропустить эту ветвь (предполагается, что "particles[i].y[0]&lt;particle_Rx2" равно false)</MESSAGE>
        </KEYEVENT>
      </SFA>
      <SFA>
        <FILEPATH>c:\md\md3.0\md3.0\</FILEPATH>
        <FILENAME>md3.0.cpp</FILENAME>
        <LINE>1037</LINE>
        <COLUMN>23</COLUMN>
        <KEYEVENT>
          <ID>2</ID>
          <KIND>ветвь</KIND>
          <IMPORTANCE>Full</IMPORTANCE>
          <MESSAGE>Пропустить эту ветвь (предполагается, что "&lt;условие ветви&gt;" равно false)</MESSAGE>
        </KEYEVENT>
      </SFA>
      <SFA>
        <FILEPATH>c:\md\md3.0\md3.0\</FILEPATH>
        <FILENAME>md3.0.cpp</FILENAME>
        <LINE>1042</LINE>
        <COLUMN>23</COLUMN>
        <KEYEVENT>
          <ID>3</ID>
          <KIND>ветвь</KIND>
          <IMPORTANCE>Full</IMPORTANCE>
          <MESSAGE>Пропустить эту ветвь (предполагается, что "particles[i].z[0]&lt;particle_Rx2" равно false)</MESSAGE>
        </KEYEVENT>
      </SFA>
      <SFA>
        <FILEPATH>c:\md\md3.0\md3.0\</FILEPATH>
        <FILENAME>md3.0.cpp</FILENAME>
        <LINE>1047</LINE>
        <COLUMN>23</COLUMN>
        <KEYEVENT>
          <ID>4</ID>
          <KIND>ветвь</KIND>
          <IMPORTANCE>Full</IMPORTANCE>
          <MESSAGE>Пропустить эту ветвь (предполагается, что "&lt;условие ветви&gt;" равно false)</MESSAGE>
        </KEYEVENT>
      </SFA>
      <SFA>
        <FILEPATH>c:\md\md3.0\md3.0\</FILEPATH>
        <FILENAME>md3.0.cpp</FILENAME>
        <LINE>1052</LINE>
        <COLUMN>29</COLUMN>
        <KEYEVENT>
          <ID>5</ID>
          <KIND>ветвь</KIND>
          <IMPORTANCE>Full</IMPORTANCE>
          <MESSAGE>Пропустить эту ветвь (предполагается, что "&lt;условие ветви&gt;" равно false)</MESSAGE>
        </KEYEVENT>
      </SFA>
      <SFA>
        <FILEPATH>c:\md\md3.0\md3.0\</FILEPATH>
        <FILENAME>md3.0.cpp</FILENAME>
        <LINE>1058</LINE>
        <COLUMN>15</COLUMN>
      </SFA>
      <SFA>
        <FILEPATH>c:\md\md3.0\md3.0\</FILEPATH>
        <FILENAME>md3.0.cpp</FILENAME>
        <LINE>1058</LINE>
        <COLUMN>24</COLUMN>
        <KEYEVENT>
          <ID>6</ID>
          <KIND>ветвь</KIND>
          <IMPORTANCE>Full</IMPORTANCE>
          <MESSAGE>Войти в этот цикл (предполагается "j&lt;4")</MESSAGE>
        </KEYEVENT>
      </SFA>
      <SFA>
        <FILEPATH>c:\md\md3.0\md3.0\</FILEPATH>
        <FILENAME>md3.0.cpp</FILENAME>
        <LINE>1059</LINE>
        <COLUMN>24</COLUMN>
        <KEYEVENT>
          <ID>7</ID>
          <KIND>ветвь</KIND>
          <IMPORTANCE>Full</IMPORTANCE>
          <MESSAGE>Войти в эту ветвь (предполагается "particles[i].x[j]&gt;0.000000")</MESSAGE>
        </KEYEVENT>
      </SFA>
      <SFA>
        <FILEPATH>c:\md\md3.0\md3.0\</FILEPATH>
        <FILENAME>md3.0.cpp</FILENAME>
        <LINE>1061</LINE>
        <COLUMN>9</COLUMN>
      </SFA>
      <SFA>
        <FILEPATH>c:\md\md3.0\md3.0\</FILEPATH>
        <FILENAME>md3.0.cpp</FILENAME>
        <LINE>1062</LINE>
        <COLUMN>9</COLUMN>
      </SFA>
      <SFA>
        <FILEPATH>c:\md\md3.0\md3.0\</FILEPATH>
        <FILENAME>md3.0.cpp</FILENAME>
        <LINE>1063</LINE>
        <COLUMN>9</COLUMN>
      </SFA>
      <SFA>
        <FILEPATH>c:\md\md3.0\md3.0\</FILEPATH>
        <FILENAME>md3.0.cpp</FILENAME>
        <LINE>1065</LINE>
        <COLUMN>60</COLUMN>
        <KEYEVENT>
          <ID>8</ID>
          <KIND>ветвь</KIND>
          <IMPORTANCE>Full</IMPORTANCE>
          <MESSAGE>Пропустить эту ветвь (предполагается, что "&lt;условие ветви&gt;" равно false)</MESSAGE>
        </KEYEVENT>
      </SFA>
      <SFA>
        <FILEPATH>c:\md\md3.0\md3.0\</FILEPATH>
        <FILENAME>md3.0.cpp</FILENAME>
        <LINE>1073</LINE>
        <COLUMN>13</COLUMN>
      </SFA>
      <SFA>
        <FILEPATH>c:\md\md3.0\md3.0\</FILEPATH>
        <FILENAME>md3.0.cpp</FILENAME>
        <LINE>1074</LINE>
        <COLUMN>13</COLUMN>
      </SFA>
      <SFA>
        <FILEPATH>c:\md\md3.0\md3.0\</FILEPATH>
        <FILENAME>md3.0.cpp</FILENAME>
        <LINE>1074</LINE>
        <COLUMN>24</COLUMN>
      </SFA>
      <SFA>
        <FILEPATH>c:\md\md3.0\md3.0\</FILEPATH>
        <FILENAME>md3.0.cpp</FILENAME>
        <LINE>1075</LINE>
        <COLUMN>13</COLUMN>
        <KEYEVENT>
          <ID>9</ID>
          <KIND>ветвь</KIND>
          <IMPORTANCE>Full</IMPORTANCE>
          <MESSAGE>Войти в эту ветвь (предполагается "y_box&gt;K")</MESSAGE>
        </KEYEVENT>
      </SFA>
      <SFA>
        <FILEPATH>c:\md\md3.0\md3.0\</FILEPATH>
        <FILENAME>md3.0.cpp</FILENAME>
        <LINE>1075</LINE>
        <COLUMN>24</COLUMN>
        <KEYEVENT>
          <ID>10</ID>
          <KIND>псевдоним</KIND>
          <IMPORTANCE>Essential</IMPORTANCE>
          <MESSAGE>(псевдоним) "y_box" получает значение "K"</MESSAGE>
        </KEYEVENT>
      </SFA>
      <SFA>
        <FILEPATH>c:\md\md3.0\md3.0\</FILEPATH>
        <FILENAME>md3.0.cpp</FILENAME>
        <LINE>1076</LINE>
        <COLUMN>13</COLUMN>
        <KEYEVENT>
          <ID>11</ID>
          <KIND>ветвь</KIND>
          <IMPORTANCE>Full</IMPORTANCE>
          <MESSAGE>Войти в эту ветвь (предполагается "z_box&gt;K")</MESSAGE>
        </KEYEVENT>
      </SFA>
      <SFA>
        <FILEPATH>c:\md\md3.0\md3.0\</FILEPATH>
        <FILENAME>md3.0.cpp</FILENAME>
        <LINE>1076</LINE>
        <COLUMN>24</COLUMN>
      </SFA>
      <SFA>
        <FILEPATH>c:\md\md3.0\md3.0\</FILEPATH>
        <FILENAME>md3.0.cpp</FILENAME>
        <LINE>1078</LINE>
        <COLUMN>25</COLUMN>
      </SFA>
      <SFA>
        <FILEPATH>c:\md\md3.0\md3.0\</FILEPATH>
        <FILENAME>md3.0.cpp</FILENAME>
        <LINE>1079</LINE>
        <COLUMN>25</COLUMN>
      </SFA>
      <SFA>
        <FILEPATH>c:\md\md3.0\md3.0\</FILEPATH>
        <FILENAME>md3.0.cpp</FILENAME>
        <LINE>1080</LINE>
        <COLUMN>25</COLUMN>
      </SFA>
      <SFA>
        <FILEPATH>c:\md\md3.0\md3.0\</FILEPATH>
        <FILENAME>md3.0.cpp</FILENAME>
        <LINE>1083</LINE>
        <COLUMN>7</COLUMN>
      </SFA>
      <SFA>
        <FILEPATH>c:\md\md3.0\md3.0\</FILEPATH>
        <FILENAME>md3.0.cpp</FILENAME>
        <LINE>1084</LINE>
        <COLUMN>48</COLUMN>
        <KEYEVENT>
          <ID>12</ID>
          <KIND>использование</KIND>
          <IMPORTANCE>Essential</IMPORTANCE>
          <MESSAGE>Недопустимая операция записи в "boxes_yz[-1]" (доступный для записи диапазон: от 0 до 99)</MESSAGE>
        </KEYEVENT>
      </SFA>
    </PATH>
  </DEFECT><DEFECT>
    <SFA>
      <FILEPATH>c:\md\md3.0\md3.0\</FILEPATH>
      <FILENAME>md3.0.cpp</FILENAME>
      <LINE>1147</LINE>
      <COLUMN>7</COLUMN>
    </SFA>
    <DEFECTCODE>6031</DEFECTCODE>
    <DESCRIPTION>Возвращаемое значение пропущено: "fscanf".</DESCRIPTION>
    <FUNCTION>load_seed</FUNCTION>
    <DECORATED>?load_seed@@YAXV?$basic_string@DU?$char_traits@D@std@@V?$allocator@D@2@@std@@@Z</DECORATED>
    <FUNCLINE>1126</FUNCLINE>
    <PATH></PATH>
  </DEFECT><DEFECT>
    <SFA>
      <FILEPATH>c:\md\md3.0\md3.0\</FILEPATH>
      <FILENAME>md3.0.cpp</FILENAME>
      <LINE>1150</LINE>
      <COLUMN>7</COLUMN>
    </SFA>
    <DEFECTCODE>6031</DEFECTCODE>
    <DESCRIPTION>Возвращаемое значение пропущено: "fscanf".</DESCRIPTION>
    <FUNCTION>load_seed</FUNCTION>
    <DECORATED>?load_seed@@YAXV?$basic_string@DU?$char_traits@D@std@@V?$allocator@D@2@@std@@@Z</DECORATED>
    <FUNCLINE>1126</FUNCLINE>
    <PATH></PATH>
  </DEFECT><DEFECT>
    <SFA>
      <FILEPATH>c:\md\md3.0\md3.0\</FILEPATH>
      <FILENAME>md3.0.cpp</FILENAME>
      <LINE>1153</LINE>
      <COLUMN>7</COLUMN>
    </SFA>
    <DEFECTCODE>6031</DEFECTCODE>
    <DESCRIPTION>Возвращаемое значение пропущено: "fscanf".</DESCRIPTION>
    <FUNCTION>load_seed</FUNCTION>
    <DECORATED>?load_seed@@YAXV?$basic_string@DU?$char_traits@D@std@@V?$allocator@D@2@@std@@@Z</DECORATED>
    <FUNCLINE>1126</FUNCLINE>
    <PATH></PATH>
  </DEFECT><DEFECT>
    <SFA>
      <FILEPATH>c:\md\md3.0\md3.0\</FILEPATH>
      <FILENAME>md3.0.cpp</FILENAME>
      <LINE>1156</LINE>
      <COLUMN>7</COLUMN>
    </SFA>
    <DEFECTCODE>6031</DEFECTCODE>
    <DESCRIPTION>Возвращаемое значение пропущено: "fscanf".</DESCRIPTION>
    <FUNCTION>load_seed</FUNCTION>
    <DECORATED>?load_seed@@YAXV?$basic_string@DU?$char_traits@D@std@@V?$allocator@D@2@@std@@@Z</DECORATED>
    <FUNCLINE>1126</FUNCLINE>
    <PATH></PATH>
  </DEFECT><DEFECT>
    <SFA>
      <FILEPATH>c:\md\md3.0\md3.0\</FILEPATH>
      <FILENAME>md3.0.cpp</FILENAME>
      <LINE>1863</LINE>
      <COLUMN>7</COLUMN>
    </SFA>
    <DEFECTCODE>6340</DEFECTCODE>
    <DESCRIPTION>Несоответствие при подписи: "const unsigned int" передан в качестве параметра _Param_(2), хотя при вызове "printf" требуется некоторый тип "signed".</DESCRIPTION>
    <FUNCTION>image</FUNCTION>
    <DECORATED>?image@@YAXJJV?$basic_string@DU?$char_traits@D@std@@V?$allocator@D@2@@std@@@Z</DECORATED>
    <FUNCLINE>1859</FUNCLINE>
    <PATH></PATH>
  </DEFECT><DEFECT>
    <SFA>
      <FILEPATH>c:\md\md3.0\md3.0\</FILEPATH>
      <FILENAME>md3.0.cpp</FILENAME>
      <LINE>2387</LINE>
      <COLUMN>28</COLUMN>
    </SFA>
    <DEFECTCODE>6001</DEFECTCODE>
    <DESCRIPTION>Использование неинициализированной памяти "min_m".</DESCRIPTION>
    <FUNCTION>F1</FUNCTION>
    <DECORATED>?F1@@YAXNNHHHHV?$basic_string@DU?$char_traits@D@std@@V?$allocator@D@2@@std@@@Z</DECORATED>
    <FUNCLINE>2227</FUNCLINE>
    <PROBABILITY>1</PROBABILITY>
    <RANK>3</RANK>
    <CATEGORY>
      <RULECATEGORY>mspft</RULECATEGORY>
    </CATEGORY>
    <PATH>
      <SFA>
        <FILEPATH>c:\md\md3.0\md3.0\</FILEPATH>
        <FILENAME>md3.0.cpp</FILENAME>
        <LINE>2229</LINE>
        <COLUMN>8</COLUMN>
      </SFA>
      <SFA>
        <FILEPATH>c:\md\md3.0\md3.0\</FILEPATH>
        <FILENAME>md3.0.cpp</FILENAME>
        <LINE>2229</LINE>
        <COLUMN>18</COLUMN>
      </SFA>
      <SFA>
        <FILEPATH>c:\md\md3.0\md3.0\</FILEPATH>
        <FILENAME>md3.0.cpp</FILENAME>
        <LINE>2230</LINE>
        <COLUMN>10</COLUMN>
      </SFA>
      <SFA>
        <FILEPATH>c:\md\md3.0\md3.0\</FILEPATH>
        <FILENAME>md3.0.cpp</FILENAME>
        <LINE>2232</LINE>
        <COLUMN>6</COLUMN>
      </SFA>
      <SFA>
        <FILEPATH>c:\md\md3.0\md3.0\</FILEPATH>
        <FILENAME>md3.0.cpp</FILENAME>
        <LINE>2233</LINE>
        <COLUMN>6</COLUMN>
      </SFA>
      <SFA>
        <FILEPATH>c:\md\md3.0\md3.0\</FILEPATH>
        <FILENAME>md3.0.cpp</FILENAME>
        <LINE>2239</LINE>
        <COLUMN>8</COLUMN>
      </SFA>
      <SFA>
        <FILEPATH>c:\md\md3.0\md3.0\</FILEPATH>
        <FILENAME>md3.0.cpp</FILENAME>
        <LINE>2240</LINE>
        <COLUMN>8</COLUMN>
      </SFA>
      <SFA>
        <FILEPATH>c:\md\md3.0\md3.0\</FILEPATH>
        <FILENAME>md3.0.cpp</FILENAME>
        <LINE>2241</LINE>
        <COLUMN>8</COLUMN>
      </SFA>
      <SFA>
        <FILEPATH>c:\md\md3.0\md3.0\</FILEPATH>
        <FILENAME>md3.0.cpp</FILENAME>
        <LINE>2242</LINE>
        <COLUMN>10</COLUMN>
      </SFA>
      <SFA>
        <FILEPATH>c:\md\md3.0\md3.0\</FILEPATH>
        <FILENAME>md3.0.cpp</FILENAME>
        <LINE>2242</LINE>
        <COLUMN>19</COLUMN>
      </SFA>
      <SFA>
        <FILEPATH>c:\md\md3.0\md3.0\</FILEPATH>
        <FILENAME>md3.0.cpp</FILENAME>
        <LINE>2243</LINE>
        <COLUMN>7</COLUMN>
      </SFA>
      <SFA>
        <FILEPATH>c:\md\md3.0\md3.0\</FILEPATH>
        <FILENAME>md3.0.cpp</FILENAME>
        <LINE>2244</LINE>
        <COLUMN>7</COLUMN>
      </SFA>
      <SFA>
        <FILEPATH>c:\md\md3.0\md3.0\</FILEPATH>
        <FILENAME>md3.0.cpp</FILENAME>
        <LINE>2245</LINE>
        <COLUMN>7</COLUMN>
      </SFA>
      <SFA>
        <FILEPATH>c:\md\md3.0\md3.0\</FILEPATH>
        <FILENAME>md3.0.cpp</FILENAME>
        <LINE>2242</LINE>
        <COLUMN>27</COLUMN>
      </SFA>
      <SFA>
        <FILEPATH>c:\md\md3.0\md3.0\</FILEPATH>
        <FILENAME>md3.0.cpp</FILENAME>
        <LINE>2242</LINE>
        <COLUMN>19</COLUMN>
      </SFA>
      <SFA>
        <FILEPATH>c:\md\md3.0\md3.0\</FILEPATH>
        <FILENAME>md3.0.cpp</FILENAME>
        <LINE>2243</LINE>
        <COLUMN>7</COLUMN>
      </SFA>
      <SFA>
        <FILEPATH>c:\md\md3.0\md3.0\</FILEPATH>
        <FILENAME>md3.0.cpp</FILENAME>
        <LINE>2244</LINE>
        <COLUMN>7</COLUMN>
      </SFA>
      <SFA>
        <FILEPATH>c:\md\md3.0\md3.0\</FILEPATH>
        <FILENAME>md3.0.cpp</FILENAME>
        <LINE>2245</LINE>
        <COLUMN>7</COLUMN>
      </SFA>
      <SFA>
        <FILEPATH>c:\md\md3.0\md3.0\</FILEPATH>
        <FILENAME>md3.0.cpp</FILENAME>
        <LINE>2242</LINE>
        <COLUMN>27</COLUMN>
      </SFA>
      <SFA>
        <FILEPATH>c:\md\md3.0\md3.0\</FILEPATH>
        <FILENAME>md3.0.cpp</FILENAME>
        <LINE>2242</LINE>
        <COLUMN>19</COLUMN>
      </SFA>
      <SFA>
        <FILEPATH>c:\md\md3.0\md3.0\</FILEPATH>
        <FILENAME>md3.0.cpp</FILENAME>
        <LINE>2248</LINE>
        <COLUMN>8</COLUMN>
      </SFA>
      <SFA>
        <FILEPATH>c:\md\md3.0\md3.0\</FILEPATH>
        <FILENAME>md3.0.cpp</FILENAME>
        <LINE>2249</LINE>
        <COLUMN>8</COLUMN>
      </SFA>
      <SFA>
        <FILEPATH>c:\md\md3.0\md3.0\</FILEPATH>
        <FILENAME>md3.0.cpp</FILENAME>
        <LINE>2250</LINE>
        <COLUMN>8</COLUMN>
      </SFA>
      <SFA>
        <FILEPATH>c:\md\md3.0\md3.0\</FILEPATH>
        <FILENAME>md3.0.cpp</FILENAME>
        <LINE>2251</LINE>
        <COLUMN>8</COLUMN>
      </SFA>
      <SFA>
        <FILEPATH>c:\md\md3.0\md3.0\</FILEPATH>
        <FILENAME>md3.0.cpp</FILENAME>
        <LINE>2252</LINE>
        <COLUMN>8</COLUMN>
      </SFA>
      <SFA>
        <FILEPATH>c:\md\md3.0\md3.0\</FILEPATH>
        <FILENAME>md3.0.cpp</FILENAME>
        <LINE>2253</LINE>
        <COLUMN>8</COLUMN>
      </SFA>
      <SFA>
        <FILEPATH>c:\md\md3.0\md3.0\</FILEPATH>
        <FILENAME>md3.0.cpp</FILENAME>
        <LINE>2255</LINE>
        <COLUMN>6</COLUMN>
      </SFA>
      <SFA>
        <FILEPATH>c:\md\md3.0\md3.0\</FILEPATH>
        <FILENAME>md3.0.cpp</FILENAME>
        <LINE>2256</LINE>
        <COLUMN>6</COLUMN>
      </SFA>
      <SFA>
        <FILEPATH>c:\md\md3.0\md3.0\</FILEPATH>
        <FILENAME>md3.0.cpp</FILENAME>
        <LINE>2257</LINE>
        <COLUMN>6</COLUMN>
      </SFA>
      <SFA>
        <FILEPATH>c:\md\md3.0\md3.0\</FILEPATH>
        <FILENAME>md3.0.cpp</FILENAME>
        <LINE>2259</LINE>
        <COLUMN>6</COLUMN>
      </SFA>
      <SFA>
        <FILEPATH>c:\md\md3.0\md3.0\</FILEPATH>
        <FILENAME>md3.0.cpp</FILENAME>
        <LINE>2259</LINE>
        <COLUMN>23</COLUMN>
      </SFA>
      <SFA>
        <FILEPATH>c:\md\md3.0\md3.0\</FILEPATH>
        <FILENAME>md3.0.cpp</FILENAME>
        <LINE>2259</LINE>
        <COLUMN>45</COLUMN>
      </SFA>
      <SFA>
        <FILEPATH>c:\md\md3.0\md3.0\</FILEPATH>
        <FILENAME>md3.0.cpp</FILENAME>
        <LINE>2259</LINE>
        <COLUMN>68</COLUMN>
      </SFA>
      <SFA>
        <FILEPATH>c:\md\md3.0\md3.0\</FILEPATH>
        <FILENAME>md3.0.cpp</FILENAME>
        <LINE>2259</LINE>
        <COLUMN>71</COLUMN>
      </SFA>
      <SFA>
        <FILEPATH>c:\md\md3.0\md3.0\</FILEPATH>
        <FILENAME>md3.0.cpp</FILENAME>
        <LINE>2259</LINE>
        <COLUMN>75</COLUMN>
      </SFA>
      <SFA>
        <FILEPATH>c:\md\md3.0\md3.0\</FILEPATH>
        <FILENAME>md3.0.cpp</FILENAME>
        <LINE>2261</LINE>
        <COLUMN>10</COLUMN>
      </SFA>
      <SFA>
        <FILEPATH>c:\md\md3.0\md3.0\</FILEPATH>
        <FILENAME>md3.0.cpp</FILENAME>
        <LINE>2261</LINE>
        <COLUMN>25</COLUMN>
      </SFA>
      <SFA>
        <FILEPATH>c:\md\md3.0\md3.0\</FILEPATH>
        <FILENAME>md3.0.cpp</FILENAME>
        <LINE>2264</LINE>
        <COLUMN>18</COLUMN>
      </SFA>
      <SFA>
        <FILEPATH>c:\md\md3.0\md3.0\</FILEPATH>
        <FILENAME>md3.0.cpp</FILENAME>
        <LINE>2267</LINE>
        <COLUMN>23</COLUMN>
      </SFA>
      <SFA>
        <FILEPATH>c:\md\md3.0\md3.0\</FILEPATH>
        <FILENAME>md3.0.cpp</FILENAME>
        <LINE>2270</LINE>
        <COLUMN>24</COLUMN>
      </SFA>
      <SFA>
        <FILEPATH>c:\md\md3.0\md3.0\</FILEPATH>
        <FILENAME>md3.0.cpp</FILENAME>
        <LINE>2273</LINE>
        <COLUMN>10</COLUMN>
      </SFA>
      <SFA>
        <FILEPATH>c:\md\md3.0\md3.0\</FILEPATH>
        <FILENAME>md3.0.cpp</FILENAME>
        <LINE>2273</LINE>
        <COLUMN>18</COLUMN>
      </SFA>
      <SFA>
        <FILEPATH>c:\md\md3.0\md3.0\</FILEPATH>
        <FILENAME>md3.0.cpp</FILENAME>
        <LINE>2274</LINE>
        <COLUMN>17</COLUMN>
      </SFA>
      <SFA>
        <FILEPATH>c:\md\md3.0\md3.0\</FILEPATH>
        <FILENAME>md3.0.cpp</FILENAME>
        <LINE>2275</LINE>
        <COLUMN>17</COLUMN>
      </SFA>
      <SFA>
        <FILEPATH>c:\md\md3.0\md3.0\</FILEPATH>
        <FILENAME>md3.0.cpp</FILENAME>
        <LINE>2276</LINE>
        <COLUMN>17</COLUMN>
      </SFA>
      <SFA>
        <FILEPATH>c:\md\md3.0\md3.0\</FILEPATH>
        <FILENAME>md3.0.cpp</FILENAME>
        <LINE>2277</LINE>
        <COLUMN>17</COLUMN>
      </SFA>
      <SFA>
        <FILEPATH>c:\md\md3.0\md3.0\</FILEPATH>
        <FILENAME>md3.0.cpp</FILENAME>
        <LINE>2278</LINE>
        <COLUMN>17</COLUMN>
      </SFA>
      <SFA>
        <FILEPATH>c:\md\md3.0\md3.0\</FILEPATH>
        <FILENAME>md3.0.cpp</FILENAME>
        <LINE>2279</LINE>
        <COLUMN>17</COLUMN>
      </SFA>
      <SFA>
        <FILEPATH>c:\md\md3.0\md3.0\</FILEPATH>
        <FILENAME>md3.0.cpp</FILENAME>
        <LINE>2281</LINE>
        <COLUMN>25</COLUMN>
      </SFA>
      <SFA>
        <FILEPATH>c:\md\md3.0\md3.0\</FILEPATH>
        <FILENAME>md3.0.cpp</FILENAME>
        <LINE>2283</LINE>
        <COLUMN>11</COLUMN>
      </SFA>
      <SFA>
        <FILEPATH>c:\md\md3.0\md3.0\</FILEPATH>
        <FILENAME>md3.0.cpp</FILENAME>
        <LINE>2283</LINE>
        <COLUMN>19</COLUMN>
      </SFA>
      <SFA>
        <FILEPATH>c:\md\md3.0\md3.0\</FILEPATH>
        <FILENAME>md3.0.cpp</FILENAME>
        <LINE>2284</LINE>
        <COLUMN>14</COLUMN>
      </SFA>
      <SFA>
        <FILEPATH>c:\md\md3.0\md3.0\</FILEPATH>
        <FILENAME>md3.0.cpp</FILENAME>
        <LINE>2285</LINE>
        <COLUMN>14</COLUMN>
      </SFA>
      <SFA>
        <FILEPATH>c:\md\md3.0\md3.0\</FILEPATH>
        <FILENAME>md3.0.cpp</FILENAME>
        <LINE>2286</LINE>
        <COLUMN>14</COLUMN>
      </SFA>
      <SFA>
        <FILEPATH>c:\md\md3.0\md3.0\</FILEPATH>
        <FILENAME>md3.0.cpp</FILENAME>
        <LINE>2283</LINE>
        <COLUMN>31</COLUMN>
      </SFA>
      <SFA>
        <FILEPATH>c:\md\md3.0\md3.0\</FILEPATH>
        <FILENAME>md3.0.cpp</FILENAME>
        <LINE>2283</LINE>
        <COLUMN>19</COLUMN>
      </SFA>
      <SFA>
        <FILEPATH>c:\md\md3.0\md3.0\</FILEPATH>
        <FILENAME>md3.0.cpp</FILENAME>
        <LINE>2284</LINE>
        <COLUMN>14</COLUMN>
      </SFA>
      <SFA>
        <FILEPATH>c:\md\md3.0\md3.0\</FILEPATH>
        <FILENAME>md3.0.cpp</FILENAME>
        <LINE>2285</LINE>
        <COLUMN>14</COLUMN>
      </SFA>
      <SFA>
        <FILEPATH>c:\md\md3.0\md3.0\</FILEPATH>
        <FILENAME>md3.0.cpp</FILENAME>
        <LINE>2286</LINE>
        <COLUMN>14</COLUMN>
      </SFA>
      <SFA>
        <FILEPATH>c:\md\md3.0\md3.0\</FILEPATH>
        <FILENAME>md3.0.cpp</FILENAME>
        <LINE>2283</LINE>
        <COLUMN>31</COLUMN>
      </SFA>
      <SFA>
        <FILEPATH>c:\md\md3.0\md3.0\</FILEPATH>
        <FILENAME>md3.0.cpp</FILENAME>
        <LINE>2283</LINE>
        <COLUMN>19</COLUMN>
      </SFA>
      <SFA>
        <FILEPATH>c:\md\md3.0\md3.0\</FILEPATH>
        <FILENAME>md3.0.cpp</FILENAME>
        <LINE>2273</LINE>
        <COLUMN>27</COLUMN>
      </SFA>
      <SFA>
        <FILEPATH>c:\md\md3.0\md3.0\</FILEPATH>
        <FILENAME>md3.0.cpp</FILENAME>
        <LINE>2273</LINE>
        <COLUMN>18</COLUMN>
      </SFA>
      <SFA>
        <FILEPATH>c:\md\md3.0\md3.0\</FILEPATH>
        <FILENAME>md3.0.cpp</FILENAME>
        <LINE>2274</LINE>
        <COLUMN>17</COLUMN>
      </SFA>
      <SFA>
        <FILEPATH>c:\md\md3.0\md3.0\</FILEPATH>
        <FILENAME>md3.0.cpp</FILENAME>
        <LINE>2275</LINE>
        <COLUMN>17</COLUMN>
      </SFA>
      <SFA>
        <FILEPATH>c:\md\md3.0\md3.0\</FILEPATH>
        <FILENAME>md3.0.cpp</FILENAME>
        <LINE>2276</LINE>
        <COLUMN>17</COLUMN>
      </SFA>
      <SFA>
        <FILEPATH>c:\md\md3.0\md3.0\</FILEPATH>
        <FILENAME>md3.0.cpp</FILENAME>
        <LINE>2277</LINE>
        <COLUMN>17</COLUMN>
      </SFA>
      <SFA>
        <FILEPATH>c:\md\md3.0\md3.0\</FILEPATH>
        <FILENAME>md3.0.cpp</FILENAME>
        <LINE>2278</LINE>
        <COLUMN>17</COLUMN>
      </SFA>
      <SFA>
        <FILEPATH>c:\md\md3.0\md3.0\</FILEPATH>
        <FILENAME>md3.0.cpp</FILENAME>
        <LINE>2279</LINE>
        <COLUMN>17</COLUMN>
      </SFA>
      <SFA>
        <FILEPATH>c:\md\md3.0\md3.0\</FILEPATH>
        <FILENAME>md3.0.cpp</FILENAME>
        <LINE>2281</LINE>
        <COLUMN>25</COLUMN>
      </SFA>
      <SFA>
        <FILEPATH>c:\md\md3.0\md3.0\</FILEPATH>
        <FILENAME>md3.0.cpp</FILENAME>
        <LINE>2283</LINE>
        <COLUMN>11</COLUMN>
      </SFA>
      <SFA>
        <FILEPATH>c:\md\md3.0\md3.0\</FILEPATH>
        <FILENAME>md3.0.cpp</FILENAME>
        <LINE>2283</LINE>
        <COLUMN>19</COLUMN>
      </SFA>
      <SFA>
        <FILEPATH>c:\md\md3.0\md3.0\</FILEPATH>
        <FILENAME>md3.0.cpp</FILENAME>
        <LINE>2273</LINE>
        <COLUMN>27</COLUMN>
      </SFA>
      <SFA>
        <FILEPATH>c:\md\md3.0\md3.0\</FILEPATH>
        <FILENAME>md3.0.cpp</FILENAME>
        <LINE>2273</LINE>
        <COLUMN>18</COLUMN>
      </SFA>
      <SFA>
        <FILEPATH>c:\md\md3.0\md3.0\</FILEPATH>
        <FILENAME>md3.0.cpp</FILENAME>
        <LINE>2296</LINE>
        <COLUMN>11</COLUMN>
      </SFA>
      <SFA>
        <FILEPATH>c:\md\md3.0\md3.0\</FILEPATH>
        <FILENAME>md3.0.cpp</FILENAME>
        <LINE>2297</LINE>
        <COLUMN>12</COLUMN>
      </SFA>
      <SFA>
        <FILEPATH>c:\md\md3.0\md3.0\</FILEPATH>
        <FILENAME>md3.0.cpp</FILENAME>
        <LINE>2297</LINE>
        <COLUMN>21</COLUMN>
      </SFA>
      <SFA>
        <FILEPATH>c:\md\md3.0\md3.0\</FILEPATH>
        <FILENAME>md3.0.cpp</FILENAME>
        <LINE>2314</LINE>
        <COLUMN>12</COLUMN>
      </SFA>
      <SFA>
        <FILEPATH>c:\md\md3.0\md3.0\</FILEPATH>
        <FILENAME>md3.0.cpp</FILENAME>
        <LINE>2314</LINE>
        <COLUMN>21</COLUMN>
      </SFA>
      <SFA>
        <FILEPATH>c:\md\md3.0\md3.0\</FILEPATH>
        <FILENAME>md3.0.cpp</FILENAME>
        <LINE>2316</LINE>
        <COLUMN>9</COLUMN>
      </SFA>
      <SFA>
        <FILEPATH>c:\md\md3.0\md3.0\</FILEPATH>
        <FILENAME>md3.0.cpp</FILENAME>
        <LINE>2317</LINE>
        <COLUMN>9</COLUMN>
      </SFA>
      <SFA>
        <FILEPATH>c:\md\md3.0\md3.0\</FILEPATH>
        <FILENAME>md3.0.cpp</FILENAME>
        <LINE>2321</LINE>
        <COLUMN>12</COLUMN>
      </SFA>
      <SFA>
        <FILEPATH>c:\md\md3.0\md3.0\</FILEPATH>
        <FILENAME>md3.0.cpp</FILENAME>
        <LINE>2321</LINE>
        <COLUMN>21</COLUMN>
      </SFA>
      <SFA>
        <FILEPATH>c:\md\md3.0\md3.0\</FILEPATH>
        <FILENAME>md3.0.cpp</FILENAME>
        <LINE>2325</LINE>
        <COLUMN>12</COLUMN>
      </SFA>
      <SFA>
        <FILEPATH>c:\md\md3.0\md3.0\</FILEPATH>
        <FILENAME>md3.0.cpp</FILENAME>
        <LINE>2326</LINE>
        <COLUMN>12</COLUMN>
      </SFA>
      <SFA>
        <FILEPATH>c:\md\md3.0\md3.0\</FILEPATH>
        <FILENAME>md3.0.cpp</FILENAME>
        <LINE>2326</LINE>
        <COLUMN>21</COLUMN>
      </SFA>
      <SFA>
        <FILEPATH>c:\md\md3.0\md3.0\</FILEPATH>
        <FILENAME>md3.0.cpp</FILENAME>
        <LINE>2314</LINE>
        <COLUMN>28</COLUMN>
      </SFA>
      <SFA>
        <FILEPATH>c:\md\md3.0\md3.0\</FILEPATH>
        <FILENAME>md3.0.cpp</FILENAME>
        <LINE>2314</LINE>
        <COLUMN>21</COLUMN>
      </SFA>
      <SFA>
        <FILEPATH>c:\md\md3.0\md3.0\</FILEPATH>
        <FILENAME>md3.0.cpp</FILENAME>
        <LINE>2358</LINE>
        <COLUMN>11</COLUMN>
      </SFA>
      <SFA>
        <FILEPATH>c:\md\md3.0\md3.0\</FILEPATH>
        <FILENAME>md3.0.cpp</FILENAME>
        <LINE>2358</LINE>
        <COLUMN>20</COLUMN>
      </SFA>
      <SFA>
        <FILEPATH>c:\md\md3.0\md3.0\</FILEPATH>
        <FILENAME>md3.0.cpp</FILENAME>
        <LINE>2367</LINE>
        <COLUMN>7</COLUMN>
        <KEYEVENT>
          <ID>1</ID>
          <KIND>объявление</KIND>
          <IMPORTANCE>Essential</IMPORTANCE>
          <MESSAGE>Инициализация "min_m" не выполнена</MESSAGE>
        </KEYEVENT>
      </SFA>
      <SFA>
        <FILEPATH>c:\md\md3.0\md3.0\</FILEPATH>
        <FILENAME>md3.0.cpp</FILENAME>
        <LINE>2367</LINE>
        <COLUMN>14</COLUMN>
      </SFA>
      <SFA>
        <FILEPATH>c:\md\md3.0\md3.0\</FILEPATH>
        <FILENAME>md3.0.cpp</FILENAME>
        <LINE>2368</LINE>
        <COLUMN>9</COLUMN>
      </SFA>
      <SFA>
        <FILEPATH>c:\md\md3.0\md3.0\</FILEPATH>
        <FILENAME>md3.0.cpp</FILENAME>
        <LINE>2368</LINE>
        <COLUMN>20</COLUMN>
      </SFA>
      <SFA>
        <FILEPATH>c:\md\md3.0\md3.0\</FILEPATH>
        <FILENAME>md3.0.cpp</FILENAME>
        <LINE>2368</LINE>
        <COLUMN>31</COLUMN>
      </SFA>
      <SFA>
        <FILEPATH>c:\md\md3.0\md3.0\</FILEPATH>
        <FILENAME>md3.0.cpp</FILENAME>
        <LINE>2368</LINE>
        <COLUMN>35</COLUMN>
      </SFA>
      <SFA>
        <FILEPATH>c:\md\md3.0\md3.0\</FILEPATH>
        <FILENAME>md3.0.cpp</FILENAME>
        <LINE>2368</LINE>
        <COLUMN>39</COLUMN>
      </SFA>
      <SFA>
        <FILEPATH>c:\md\md3.0\md3.0\</FILEPATH>
        <FILENAME>md3.0.cpp</FILENAME>
        <LINE>2368</LINE>
        <COLUMN>45</COLUMN>
      </SFA>
      <SFA>
        <FILEPATH>c:\md\md3.0\md3.0\</FILEPATH>
        <FILENAME>md3.0.cpp</FILENAME>
        <LINE>2368</LINE>
        <COLUMN>59</COLUMN>
      </SFA>
      <SFA>
        <FILEPATH>c:\md\md3.0\md3.0\</FILEPATH>
        <FILENAME>md3.0.cpp</FILENAME>
        <LINE>2368</LINE>
        <COLUMN>66</COLUMN>
      </SFA>
      <SFA>
        <FILEPATH>c:\md\md3.0\md3.0\</FILEPATH>
        <FILENAME>md3.0.cpp</FILENAME>
        <LINE>2376</LINE>
        <COLUMN>11</COLUMN>
      </SFA>
      <SFA>
        <FILEPATH>c:\md\md3.0\md3.0\</FILEPATH>
        <FILENAME>md3.0.cpp</FILENAME>
        <LINE>2376</LINE>
        <COLUMN>20</COLUMN>
        <KEYEVENT>
          <ID>2</ID>
          <KIND>ветвь</KIND>
          <IMPORTANCE>Full</IMPORTANCE>
          <MESSAGE>Пропустить этот цикл (предполагается, что "m&lt;particles_count" равно false)</MESSAGE>
        </KEYEVENT>
      </SFA>
      <SFA>
        <FILEPATH>c:\md\md3.0\md3.0\</FILEPATH>
        <FILENAME>md3.0.cpp</FILENAME>
        <LINE>2387</LINE>
        <COLUMN>28</COLUMN>
        <KEYEVENT>
          <ID>3</ID>
          <KIND>использование</KIND>
          <IMPORTANCE>Essential</IMPORTANCE>
          <MESSAGE>"min_m" используется, но, возможно, не инициализировано</MESSAGE>
        </KEYEVENT>
      </SFA>
    </PATH>
  </DEFECT></DEFECTS>